{
  "channels": [
    {
      "name": "release",
      "latestVersionName": "v1.7.2",
      "latestVersionCode": 49,
      "minAPI": 21,
      "url": "https://github.com/truefedex/tv-bro/releases/download/v1.7.2/tvbro1.7.2.apk"
    },
    {
      "name": "beta",
      "latestVersionName": "v1.8.0",
      "latestVersionCode": 51,
      "minAPI": 21,
      "url": "https://github.com/truefedex/tv-bro/releases/download/v1.8.0/tvbro1.8.0.apk"
    }
  ],

  "changelog": [
    {
      "versionCode": 51,
      "versionName": "v1.8.0",
      "changes": "* Incognito mode implemented\n* Settings: added option to keep screen always on (thank you  Sebastian Niemann for pull request !)\n* German translation (thank you peat80 for pull request !)\n* Fixed problem with voice recognition on android >= 11 (now look a bit changed but functionality recovered)\n* Icon look changed to declare support for Ukraine (explanation by link in settings)"
    },
    {
      "versionCode": 49,
      "versionName": "v1.7.2",
      "changes": "* Added ability to set search engine as homepage (thank you E-D-W-I-N for pull request !)\n* Dark theme tuning/fixing/backporting; should now work on pre-Android 10 devices\n* Improvement: auto retry download, this helps on some sites\n* Fix: crash on download on Fire TV (thank you tsynik for crashlog)\n* Fix: unability to select tab with mouse (thank you xvkong for foundings)\n* Fix for not showing ssl errors on some pages\n* Fix for tabs fast scrolling issues"
    },
    {
      "versionCode": 48,
      "versionName": "v1.7.1",
      "changes": "* Bugfix"
    }
  ]
}